{"list":" font-light text-gray-700 bg-white flex items-center flex-wrap px-4 py-5 container mx-auto font-medium hover:text-blue-800 mr-auto text-2xl text-blue-600 uppercase hover:bg-blue-600 hover:text-white px-3 py-2 rounded lg:hidden block border-b-2 border-current my-1 w-6 lg:flex lg:items-center lg:space-x-4 lg:space-y-0 lg:w-auto space-y-2 w-full hidden flex-col lg:flex-row hover:text-blue-600 lg:px-4 px-0 bg-blue-600 inline-block px-5 text-white hover:bg-blue-700 bg-gray-100 relative text-gray-500 pt-24 -mx-4 text-center lg:w-8/12 xl:w-6/12 font-normal mb-4 text-6xl text-gray-900 mb-6 text-lg hover:bg-blue-800 hover:bg-gray-200 -mb-40 mt-10 p-16 rounded-lg h-auto h-20 bg-opacity-25 pb-20 pt-40 lg:w-9/12 mb-2 text-5xl p-4 xl:w-3/12 sm:w-6/12 border group px-8 py-16 group-hover:text-white h-10 w-10 text-xl text-sm border-b text-gray-600 py-10 ml-auto lg:order-2 lg:w-6/12 lg:order-1 lg:w-5/12 mb-3 lg:mr-4 h-16 text-blue-700 bg-blue-700 xl:order-2 -mt-48 max-w-full w-7/12 xl:w-9/12 xl:order-1 sm:w-4/12 h-12 w-12 text-gray-100 bg-gray-50 py-20 text-4xl mb-8 z-0 lg:px-10 flex-row nowrap overflow-hidden flex-grow-0 flex-shrink-0 md:w-6/12 xl:w-4/12 p-10 shadow-lg mb-5 mr-3 rounded-full w-20 font-semibold leading-tight absolute bottom-0 mr-6 right-0 text-gray-300 h-full justify-center left-0 p-1 text-gray-800 bg-gray-200 group-hover:bg-blue-600 h-6 mt-6 space-x-1 py-3 bg-gray-400 h-1 transition-all px-6 rounded-sm xl:w-10/12 lg:w-4/12 align-top leading-none bg-gray-900 px-2 py-4 pb-12 pt-10 mb-10 space-y-4 bg-gray-800 hover:bg-gray-700 pt-12 hover:text-gray-400 text-3xl md:w-3/12 xl:w-2/12 border-2 border-gray-400 appearance-none border-blue-600 flex-1 outline-none p-2 h-4 w-4 font-bold inline-flex space-x-3 hover:text-blue-400 h-5 w-5 opacity-25 md:flex-1 sm:w-auto","map":{"font-light":true,"text-gray-700":true,"bg-white":true,"flex":true,"items-center":true,"flex-wrap":true,"px-4":true,"py-5":true,"container":true,"mx-auto":true,"font-medium":true,"hover:text-blue-800":true,"mr-auto":true,"text-2xl":true,"text-blue-600":true,"uppercase":true,"hover:bg-blue-600":true,"hover:text-white":true,"px-3":true,"py-2":true,"rounded":true,"lg:hidden":true,"block":true,"border-b-2":true,"border-current":true,"my-1":true,"w-6":true,"lg:flex":true,"lg:items-center":true,"lg:space-x-4":true,"lg:space-y-0":true,"lg:w-auto":true,"space-y-2":true,"w-full":true,"hidden":true,"flex-col":true,"lg:flex-row":true,"hover:text-blue-600":true,"lg:px-4":true,"px-0":true,"bg-blue-600":true,"inline-block":true,"px-5":true,"text-white":true,"hover:bg-blue-700":true,"bg-gray-100":true,"relative":true,"text-gray-500":true,"pt-24":true,"-mx-4":true,"text-center":true,"lg:w-8/12":true,"xl:w-6/12":true,"font-normal":true,"mb-4":true,"text-6xl":true,"text-gray-900":true,"mb-6":true,"text-lg":true,"hover:bg-blue-800":true,"hover:bg-gray-200":true,"-mb-40":true,"mt-10":true,"p-16":true,"rounded-lg":true,"h-auto":true,"h-20":true,"bg-opacity-25":true,"pb-20":true,"pt-40":true,"lg:w-9/12":true,"mb-2":true,"text-5xl":true,"p-4":true,"xl:w-3/12":true,"sm:w-6/12":true,"border":true,"group":true,"px-8":true,"py-16":true,"group-hover:text-white":true,"h-10":true,"w-10":true,"text-xl":true,"text-sm":true,"border-b":true,"text-gray-600":true,"py-10":true,"ml-auto":true,"lg:order-2":true,"lg:w-6/12":true,"lg:order-1":true,"lg:w-5/12":true,"mb-3":true,"lg:mr-4":true,"h-16":true,"text-blue-700":true,"bg-blue-700":true,"xl:order-2":true,"-mt-48":true,"max-w-full":true,"w-7/12":true,"xl:w-9/12":true,"xl:order-1":true,"sm:w-4/12":true,"h-12":true,"w-12":true,"text-gray-100":true,"bg-gray-50":true,"py-20":true,"text-4xl":true,"mb-8":true,"z-0":true,"lg:px-10":true,"flex-row":true,"nowrap":true,"overflow-hidden":true,"flex-grow-0":true,"flex-shrink-0":true,"md:w-6/12":true,"xl:w-4/12":true,"p-10":true,"shadow-lg":true,"mb-5":true,"mr-3":true,"rounded-full":true,"w-20":true,"font-semibold":true,"leading-tight":true,"absolute":true,"bottom-0":true,"mr-6":true,"right-0":true,"text-gray-300":true,"h-full":true,"justify-center":true,"left-0":true,"p-1":true,"text-gray-800":true,"bg-gray-200":true,"group-hover:bg-blue-600":true,"h-6":true,"mt-6":true,"space-x-1":true,"py-3":true,"bg-gray-400":true,"h-1":true,"transition-all":true,"px-6":true,"rounded-sm":true,"xl:w-10/12":true,"lg:w-4/12":true,"align-top":true,"leading-none":true,"bg-gray-900":true,"px-2":true,"py-4":true,"pb-12":true,"pt-10":true,"mb-10":true,"space-y-4":true,"bg-gray-800":true,"hover:bg-gray-700":true,"pt-12":true,"hover:text-gray-400":true,"text-3xl":true,"md:w-3/12":true,"xl:w-2/12":true,"border-2":true,"border-gray-400":true,"appearance-none":true,"border-blue-600":true,"flex-1":true,"outline-none":true,"p-2":true,"h-4":true,"w-4":true,"font-bold":true,"inline-flex":true,"space-x-3":true,"hover:text-blue-400":true,"h-5":true,"w-5":true,"opacity-25":true,"md:flex-1":true,"sm:w-auto":true}}